<?xml version="1.0" encoding="utf-8"?>
<DT11 Behavior="Searching" Collision="0" Doubtful="0" Length="34" Status="Alive">
   <Event Type="Forward">
      <pose>[736 455;737 455;738 454;739 453;740 452;741 452;742 452;743 451;744 450;745 449;746 448;746 447;747 446;747 445;747 444;747 443;747 442;748 441;749 440;750 439;751 439;752 439;753 439;754 439;755 439]</pose>
      <pose>[742 452;743 451;744 450;745 449;746 448;746 447;746 446;746 445;746 444;746 443;747 442;748 441;749 441;750 440;751 440;752 439;753 439;754 438;755 437;756 436;756 435;757 434;757 433;757 432]</pose>
   </Event>
   <Event Type="Stopped">
      <pose>[743 452;744 451;745 450;746 449;746 448;746 447;746 446;746 445;746 444;747 443;747 442;748 441;749 441;750 440;751 440;752 439;753 438;754 437;755 436;755 435;756 434;757 433;757 432]</pose>
      <pose>[745 449;746 448;746 447;746 446;746 445;746 444;747 443;748 442;749 441;750 440;751 440;752 439;753 438;754 437;755 436;756 435;756 434;757 433;757 432]</pose>
      <pose>[743 451;744 450;745 450;746 449;746 448;746 447;746 446;747 445;747 444;747 443;747 442;748 441;749 440;750 440;751 439;752 439;753 438;754 438;755 437;756 436;756 435;756 434;756 433]</pose>
      <pose>[741 451;742 451;743 451;744 451;745 451;746 450;746 449;746 448;747 447;747 446;747 445;747 444;747 443;747 442;748 441;749 440;750 439;751 439;752 438;753 438;754 438]</pose>
      <pose>[739 452;740 452;741 452;742 451;743 451;744 451;745 450;746 449;746 448;747 447;747 446;747 445;747 444;747 443;747 442;748 441;749 440;750 439;751 438;752 438;753 438;754 438]</pose>
      <pose>[740 452;741 452;742 451;743 451;744 451;745 450;746 449;747 448;747 447;747 446;747 445;747 444;747 443;747 442;748 441;749 440;750 439;751 439;752 439;753 439]</pose>
   </Event>
   <Event Type="Backwards">
      <pose>[737 456;737 455;738 454;738 453;739 452;740 451;741 450;742 450;743 450;744 450;745 449;746 449;747 448;748 447;748 446;748 445;748 444;748 443;748 442;748 441;749 440;750 439]</pose>
   </Event>
   <Event Type="Stopped">
      <pose>[736 458;737 457;738 456;739 455;739 454;739 453;739 452;740 451;741 450;742 449;743 449;744 449;745 448;746 448;747 447;748 446;749 445;749 444;749 443;749 442;749 441]</pose>
   </Event>
   <Event Type="Backwards">
      <pose>[731 456;732 457;733 458;734 458;735 458;736 458;737 457;738 456;739 455;739 454;739 453;739 452;740 451;740 450;741 449;742 448;743 447;744 447;745 447;746 447;747 447;748 447]</pose>
   </Event>
   <Event Type="Stopped">
      <pose>[730 456;731 456;732 456;733 457;734 458;735 458;736 458;737 457;738 456;739 455;740 454;740 453;740 452;740 451;740 450;741 449;742 448;743 447;744 447;745 446]</pose>
      <pose>[731 456;732 457;733 457;734 458;735 458;736 458;737 457;738 456;739 455;740 454;740 453;740 452;740 451;741 450;741 449;742 448;743 448;744 448;745 448;746 448]</pose>
      <pose>[731 456;732 457;733 458;734 458;735 458;736 458;737 457;738 456;739 455;739 454;739 453;739 452;740 451;741 450;742 449;743 448;744 448;745 448;746 448;747 448;748 447;749 446]</pose>
      <pose>[732 457;733 458;734 458;735 457;736 457;737 456;738 455;739 454;739 453;739 452;740 451;741 450;742 449;743 448;744 448;745 448;746 448;747 447;748 446;749 445;750 444;751 444]</pose>
   </Event>
   <Event Type="Backwards">
      <pose>[729 455;730 456;731 456;732 456;733 457;734 458;735 458;736 458;737 457;738 456;739 455;739 454;740 453;740 452;740 451;741 450;742 449;743 448;744 447;745 447;746 447;747 447]</pose>
      <pose>[726 459;726 458;726 457;726 456;727 455;728 455;729 455;730 455;731 455;732 456;733 456;734 456;735 457;736 457;737 457;738 457;739 456;740 455;740 454;741 453;741 452;741 451;741 450;741 449]</pose>
      <pose>[725 465;726 464;727 463;727 462;727 461;727 460;727 459;727 458;727 457;727 456;728 455;729 455;730 455;731 455;732 455;733 456;734 456;735 456;736 456;737 456;738 456;739 456]</pose>
      <pose>[721 465;722 465;723 466;724 466;725 466;726 465;726 464;726 463;727 462;727 461;727 460;727 459;727 458;728 457;728 456;729 455;730 454;731 454;732 454;733 454;734 455;735 456;735 457]</pose>
   </Event>
   <Event Type="Forward">
      <pose>[725 465;726 464;727 463;727 462;727 461;727 460;727 459;727 458;728 457;728 456;729 455;730 454;731 454;732 455;733 456;733 457;732 458;731 459;730 460;730 461]</pose>
   </Event>
   <Event Type="Rare">
      <pose>[727 459;727 458;727 457;728 456;729 455;730 455;731 455;732 456;732 457;732 458;731 459;730 460;729 461;728 462;728 463;728 464;728 465]</pose>
   </Event>
   <Event Type="Forward">
      <pose>[729 454;730 454;731 454;732 455;732 456;732 457;731 458;730 459;729 460;728 461;728 462;728 463;728 464;729 465;729 466;730 467;731 468;731 469;732 470]</pose>
   </Event>
   <Event Type="Backwards">
      <pose>[732 454;732 455;732 456;732 457;731 458;731 459;730 460;729 461;729 462;729 463;729 464;729 465;730 466;730 467;731 468;731 469;731 470;731 471;730 472;730 473;730 474;730 475;730 476;730 477;731 478;732 479]</pose>
   </Event>
   <Event Type="Forward">
      <pose>[730 457;730 458;730 459;730 460;730 461;731 462;731 463;731 464;731 465;731 466;730 467;730 468;730 469;729 470;729 471;729 472;729 473;729 474;730 475;731 476;732 477;733 478;734 479;735 480]</pose>
      <pose>[730 460;730 461;730 462;730 463;730 464;730 465;730 466;729 467;729 468;729 469;729 470;729 471;729 472;729 473;730 474;731 475;732 476;733 477;734 478;734 479;735 480;735 481;735 482;734 483;733 484]</pose>
      <pose>[730 463;730 464;730 465;730 466;729 467;729 468;729 469;729 470;729 471;729 472;729 473;730 474;731 475;732 476;733 477;734 478;734 479;734 480;734 481;733 482;733 483;733 484;733 485;733 486;733 487;734 488]</pose>
      <pose>[730 465;729 466;729 467;729 468;729 469;729 470;729 471;729 472;730 473;731 474;732 475;733 476;733 477;733 478;733 479;733 480;733 481;733 482;733 483;733 484;733 485;733 486;733 487;734 488;735 489]</pose>
   </Event>
   <Event Type="Stopped">
      <pose>[729 465;729 466;729 467;729 468;729 469;729 470;729 471;730 472;730 473;731 474;732 475;733 476;733 477;733 478;733 479;733 480;733 481;733 482;733 483;733 484;733 485;734 486;735 487;735 488]</pose>
      <pose>[729 469;729 470;729 471;730 472;730 473;731 474;732 475;733 476;733 477;733 478;733 479;733 480;733 481;733 482;733 483;733 484;734 485;734 486;735 487;735 488;735 489;735 490;735 491]</pose>
      <pose>[730 467;729 468;729 469;729 470;729 471;730 472;730 473;731 474;732 475;733 476;733 477;733 478;733 479;733 480;733 481;733 482;733 483;734 484;734 485;734 486;735 487;735 488;735 489;734 490;733 491]</pose>
   </Event>
   <Model>
      <Resize>3</Resize>
      <Weight>[2;2;2.24000000953674;2.24000000953674;2.24000000953674;2.24000000953674;2.82999992370605;3;3;3.16000008583069;3.60999989509583;3.60999989509583;4.23999977111816;4.23999977111816;4.23999977111816;4.23999977111816;4.23999977111816;4.46999979019165;5;5;5;5;5;5;5;5;5;5;5;4.11999988555908;4.46999979019165;4.23999977111816;4.23999977111816;5;5;5;4.11999988555908;4.46999979019165;4.23999977111816;5;5;4.46999979019165;5;5;5;5;5;5;4.46999979019165;4.23999977111816;4.23999977111816;4.23999977111816;4.23999977111816;4.23999977111816;4.46999979019165;4.11999988555908;5;5;4.23999977111816;3.60999989509583;2.82999992370605;3.16000008583069;3;3;2.82999992370605;2.24000000953674;2.24000000953674;2.24000000953674;2.82999992370605;2.24000000953674;2;2]</Weight>
      <Colors>[34;33;30;30;29;28;25;24;22;18;18;17;18;20;21;22;21;20;19;18;17;17;16;15;15;15;16;17;18;19;18;19;20;20;19;18;17;16;14;14;14;14;13;13;13;13;14;15;16;18;18;15;12;10;8;8;8;9;11;13;16;16;18;21;23;27;25;23;26;28;30;33]</Colors>
   </Model>
</DT11>