<?xml version="1.0" encoding="utf-8"?>
<DT5 Behavior="Searching" Collision="0" Doubtful="6.91" Length="26" Status="Alive">
   <Event Type="Rare">
      <pose>[742 225;741 225;740 225;739 226;738 226;737 226;736 227;735 228;734 228;733 228;732 227;731 227;730 226;729 226;728 225;727 225;726 225;725 225;724 225;723 226;722 227;722 228;722 229;722 230;723 231;724 232;725 233;726 233;727 233;728 232;729 232;730 231;731 230]</pose>
      <pose>[739 223;738 224;737 225;736 225;735 226;734 226;733 226;732 226;731 226;730 225;729 225;728 225;727 225;726 225;725 225;724 225;723 226;722 227;722 228;722 229;722 230;723 231;724 232;725 233;726 233;727 233;728 232;729 232;730 231;731 230;732 229;733 229]</pose>
   </Event>
   <Event Type="Backwards">
      <pose>[746 225;745 225;744 224;743 224;742 224;741 224;740 224;739 224;738 224;737 224;736 225;735 225;734 225;733 225;732 225;731 225;730 225;729 225;728 226;727 226;726 226;725 226;724 227;723 228;722 229;722 230;722 231;723 232;724 233;725 233;726 233;727 233;728 233;729 232;730 231;731 231]</pose>
   </Event>
   <Event Type="Stopped">
      <pose>[750 223;749 224;748 224;747 224;746 224;745 224;744 224;743 224;742 224;741 224;740 224;739 224;738 224;737 225;736 225;735 225;734 225;733 226;732 226;731 226;730 226;729 226;728 226;727 226;726 226;725 226;724 227;723 228;723 229;723 230;723 231;724 232;725 233;726 233;727 233;728 232;729 232]</pose>
   </Event>
   <Event Type="Rare">
      <pose>[744 224;743 224;742 225;741 225;740 225;739 226;738 226;737 226;736 226;735 226;734 226;733 225;732 225;731 225;730 225;729 225;728 225;727 225;726 225;725 226;724 227;723 228;723 229;723 230;723 231;724 232;725 233;726 233;727 233;728 233;729 232;730 231;731 231;732 230]</pose>
      <pose>[742 229;742 228;741 227;740 226;739 225;738 225;737 225;736 225;735 225;734 225;733 225;732 225;731 225;730 225;729 225;728 225;727 225;726 225;725 226;724 227;723 228;723 229;723 230;723 231;723 232;724 233;725 233;726 233;727 233;728 233;729 232;730 232;731 231;732 230;733 229;733 228]</pose>
   </Event>
   <Event Type="Backwards">
      <pose>[739 232;740 231;741 230;741 229;741 228;740 227;739 226;738 225;737 225;736 224;735 224;734 224;733 224;732 224;731 224;730 224;729 225;728 225;727 225;726 225;725 226;724 227;723 228;723 229;723 230;723 231;724 232;725 233;726 233;727 233;728 233;729 233]</pose>
      <pose>[736 233;737 233;738 232;739 231;740 230;740 229;740 228;740 227;740 226;739 225;738 224;737 224;736 223;735 223;734 223;733 224;732 224;731 224;730 224;729 225;728 225;727 225;726 226;725 226;724 227;723 228;723 229;723 230;723 231;723 232;724 233;725 234;726 234]</pose>
      <pose>[728 242;729 241;729 240;730 239;730 238;731 237;732 236;733 235;734 234;735 234;736 233;737 233;738 232;739 231;740 230;740 229;740 228;740 227;740 226;740 225;740 224;739 223;738 223;737 223;736 223;735 223;734 223;733 223;732 223;731 224;730 224;729 225;728 225;727 226;726 227;725 228;724 229]</pose>
      <pose>[729 253;729 252;729 251;729 250;729 249;728 248;728 247;728 246;728 245;728 244;728 243;728 242;728 241;728 240;728 239;729 238;730 237;731 236;732 235;733 235;734 234;735 234;736 233;737 233;738 232;739 231;740 230;740 229;740 228;740 227;740 226;740 225;739 224;738 224]</pose>
      <pose>[721 263;721 262;721 261;721 260;722 259;722 258;723 257;724 256;725 255;726 254;727 253;728 252;729 251;729 250;729 249;729 248;729 247;728 246;728 245;728 244;728 243;728 242;728 241;728 240;728 239;729 238;730 237;731 236;732 235;733 234;734 234;735 234;736 233;737 233;738 232;739 232;740 231]</pose>
      <pose>[722 263;722 262;722 261;722 260;722 259;722 258;723 257;724 256;725 255;726 254;727 253;728 252;729 251;729 250;729 249;729 248;729 247;729 246;729 245;728 244;728 243;728 242;728 241;728 240;728 239;729 238;730 237;731 236;732 235;733 235;734 234;735 234;736 233;737 232;738 231]</pose>
      <pose>[728 266;727 266;726 266;725 266;724 265;723 264;722 263;722 262;722 261;722 260;722 259;722 258;723 257;724 256;725 255;726 254;727 253;727 252;728 251;728 250;729 249;729 248;729 247;729 246;729 245;729 244;729 243;729 242;729 241;729 240;729 239;729 238;730 237;731 236;732 235;733 235;734 235;735 235]</pose>
      <pose>[730 268;729 267;728 267;727 267;726 266;725 265;724 264;723 263;722 262;722 261;722 260;722 259;722 258;723 257;724 256;725 255;726 254;727 253;727 252;728 251;728 250;728 249;729 248;729 247;729 246;729 245;729 244;729 243;729 242;729 241;729 240;729 239;729 238;730 237]</pose>
   </Event>
   <Event Type="Heading">
      <pose>[731 271;731 270;731 269;730 268;729 267;728 267;727 266;726 266;725 265;724 264;723 263;722 262;722 261;722 260;722 259;722 258;723 257;723 256;724 255;725 254;726 253;727 252;728 251;728 250;729 249;729 248;729 247;729 246;729 245;729 244;729 243;729 242;729 241;729 240;729 239;729 238;730 237]</pose>
   </Event>
   <Event Type="Stopped">
      <pose>[732 271;732 270;731 269;730 268;729 267;728 267;727 266;726 266;725 265;724 264;723 263;722 262;722 261;722 260;722 259;722 258;723 257;724 256;724 255;725 254;726 253;727 252;727 251;728 250;728 249;729 248;729 247;729 246;729 245;729 244;729 243;729 242;729 241;729 240;729 239;729 238]</pose>
      <pose>[732 274;732 273;732 272;732 271;731 270;730 269;729 268;728 267;727 266;726 265;725 264;724 263;723 262;722 261;722 260;722 259;722 258;722 257;723 256;724 255;725 254;726 253;727 252;727 251;728 250;729 249;729 248;729 247;729 246;729 245;729 244;729 243;729 242;729 241;728 240;728 239]</pose>
      <pose>[733 276;733 275;733 274;732 273;732 272;732 271;731 270;731 269;730 268;729 267;728 267;727 266;726 265;725 264;724 263;723 262;722 261;722 260;722 259;722 258;723 257;723 256;724 255;725 254;726 253;727 252;728 251;729 250;729 249;729 248;729 247;729 246;729 245;729 244;729 243;729 242;729 241]</pose>
      <pose>[735 281;735 280;735 279;734 278;734 277;733 276;733 275;732 274;732 273;732 272;731 271;731 270;731 269;730 268;729 267;728 266;727 265;726 265;725 264;724 263;723 262;722 261;722 260;722 259;722 258;722 257;723 256;724 255;725 254;725 253;726 252;727 251;728 250;729 249;729 248;729 247;729 246]</pose>
   </Event>
   <Event Type="Backwards">
      <pose>[737 283;737 282;736 281;736 280;735 279;734 278;733 277;733 276;733 275;733 274;732 273;732 272;732 271;731 270;731 269;730 268;729 267;728 266;727 266;726 265;725 264;724 263;723 262;722 261;722 260;722 259;722 258;722 257;723 256;724 255;725 254;726 253;727 252;728 251;728 250;729 249]</pose>
   </Event>
   <Event Type="Stopped">
      <pose>[739 285;739 284;738 283;738 282;737 281;736 280;735 279;734 278;733 277;733 276;733 275;732 274;732 273;732 272;732 271;731 270;731 269;730 268;729 267;728 266;727 265;726 264;725 263;724 262;723 261;723 260;723 259;723 258;723 257;723 256;724 255;725 254;726 253;727 253;728 252;729 251]</pose>
   </Event>
   <Event Type="Backwards">
      <pose>[740 290;740 289;740 288;740 287;739 286;739 285;739 284;738 283;738 282;737 281;737 280;736 279;735 278;734 277;733 276;733 275;732 274;732 273;732 272;731 271;731 270;731 269;730 268;729 267;728 266;727 265;726 264;725 263;724 262;723 261;722 260;722 259;722 258;722 257;723 256;724 255]</pose>
   </Event>
   <Event Type="Forward">
      <pose>[739 289;740 288;740 287;740 286;739 285;739 284;738 283;738 282;737 281;736 280;735 279;735 278;734 277;733 276;733 275;732 274;732 273;732 272;732 271;732 270;731 269;730 268;729 267;728 266;727 266;726 265;725 264;724 263;723 262;723 261;723 260;723 259;723 258;723 257;723 256;724 255]</pose>
      <pose>[739 283;738 282;737 282;736 281;735 280;734 279;734 278;734 277;733 276;733 275;733 274;733 273;732 272;732 271;732 270;731 269;730 268;729 267;728 267;727 266;726 265;725 264;724 263;723 262;723 261;723 260;723 259;723 258;723 257;724 256;725 255;726 254;727 253;728 252]</pose>
      <pose>[734 279;734 278;733 277;733 276;733 275;733 274;733 273;733 272;732 271;731 270;730 269;729 268;728 267;727 267;726 266;725 265;724 264;723 263;723 262;722 261;722 260;722 259;722 258;723 257;724 256;725 255;726 254;727 253;728 252;728 251;729 250;729 249;729 248;728 247;727 246;726 246]</pose>
      <pose>[733 273;733 272;732 271;731 270;730 269;729 268;728 267;727 267;726 266;725 265;724 264;723 263;722 262;722 261;722 260;722 259;723 258;723 257;724 256;725 255;726 254;726 253;727 252;728 251;729 250;729 249;729 248;728 247;727 246;726 245;725 245;724 245]</pose>
   </Event>
   <Event Type="Backwards">
      <pose>[728 278;729 278;730 277;731 276;732 275;732 274;732 273;732 272;732 271;732 270;731 269;730 268;729 267;728 267;727 266;726 265;725 264;724 263;723 262;723 261;723 260;723 259;723 258;723 257;724 256;725 255;726 254;727 253;728 252;728 251;728 250;728 249;728 248;728 247;728 246;727 245]</pose>
      <pose>[725 280;726 280;727 279;728 279;729 278;730 277;730 276;731 275;732 274;732 273;732 272;732 271;732 270;731 269;730 268;729 267;728 267;727 266;726 265;725 264;724 263;723 262;723 261;723 260;723 259;723 258;723 257;724 256;725 255;725 254;726 253;727 252;728 251;728 250;729 249]</pose>
      <pose>[723 282;724 281;725 280;726 279;727 279;728 278;729 277;730 276;731 275;732 274;732 273;732 272;732 271;732 270;731 269;730 268;729 267;728 267;727 266;726 265;725 264;724 263;723 262;723 261;723 260;723 259;723 258;723 257;723 256;724 255;725 254;726 253;727 252]</pose>
   </Event>
   <Event Type="Stopped">
      <pose>[722 286;722 285;722 284;723 283;724 282;725 281;726 280;727 279;728 278;729 277;730 276;731 275;732 274;732 273;732 272;732 271;732 270;731 269;730 268;729 267;728 267;727 266;726 265;725 264;724 263;724 262;723 261;723 260;723 259;723 258;723 257;724 256;725 255;726 254;727 253]</pose>
   </Event>
   <Model>
      <Resize>3</Resize>
      <Weight>[2;2;2.24000000953674;2.24000000953674;2.82999992370605;2.82999992370605;3.60999989509583;3.60999989509583;4.23999977111816;4.46999979019165;5;5;5;4.46999979019165;4.23999977111816;4.46999979019165;5;5;5;4.46999979019165;4.23999977111816;4.46999979019165;5;5;5;4.46999979019165;5;5.65999984741211;6;6;6;6;5.82999992370605;5;5;4.46999979019165;5;5;5;5;4.11999988555908;4.46999979019165;4.23999977111816;5;5.3899998664856;6.32000017166138;6.40000009536743;7.07000017166138;7.07000017166138;6.40000009536743;6.40000009536743;5.65999984741211;5.82999992370605;5.3899998664856;6.07999992370605;6;6;6;6;6;6;6;6.07999992370605;5.3899998664856;5.82999992370605;5.65999984741211;6.40000009536743;6.40000009536743;6.40000009536743;6.40000009536743;6.40000009536743;5.82999992370605;6.32000017166138;6.32000017166138;5.82999992370605;6.40000009536743;6.40000009536743;5.82999992370605;6.32000017166138;6.07999992370605;6;6.07999992370605;6.32000017166138;5.82999992370605;6.40000009536743;6.40000009536743;6.40000009536743;6.40000009536743;6.40000009536743;6.40000009536743;6.40000009536743;5.65999984741211;5.65999984741211;5.65999984741211;5.65999984741211;5.65999984741211;5.65999984741211;5.65999984741211;5.65999984741211;6.07999992370605;6;6;5.65999984741211;5;5.09999990463257;4.46999979019165;4.23999977111816;5;5.65999984741211;5;4.23999977111816;4.23999977111816;3.60999989509583;3.60999989509583;3.60999989509583;3.60999989509583;4.23999977111816;4.23999977111816;3.60999989509583;2.82999992370605]</Weight>
      <Colors>[32;32;32;30;27;25;23;21;21;21;20;20;20;20;19;19;19;19;19;19;19;19;19;19;19;19;18;17;17;17;17;17;17;17;13;13;13;13;13;12;11;10;10;9;10;9;8;8;7;7;6;6;5;5;5;5;5;5;5;5;5;5;5;6;7;8;9;9;10;10;11;10;10;12;14;14;13;13;13;12;11;11;11;10;10;10;11;11;11;10;9;9;9;9;9;9;9;9;9;8;9;8;9;9;10;11;14;14;16;17;18;19;20;21;24;26;26;27;28;29]</Colors>
   </Model>
</DT5>