<?xml version="1.0" encoding="utf-8"?>
<DT5 Behavior="Searching" Collision="0" Doubtful="8.5" Length="33" Status="Alive">
   <Event Type="Backwards">
      <pose>[1043 862;1042 861;1041 860;1040 860;1039 859;1038 859;1037 859;1036 858;1035 857;1034 856;1034 855;1033 854;1033 853;1032 852;1032 851;1031 850;1030 849;1029 848;1028 848;1027 847;1026 847;1025 847;1024 847;1023 846;1022 845;1021 844;1020 843]</pose>
      <pose>[1050 866;1049 866;1048 866;1047 866;1046 866;1045 865;1044 864;1044 863;1043 862;1042 861;1041 861;1040 860;1039 859;1038 859;1037 858;1036 858;1035 857;1034 856;1033 855;1033 854;1032 853;1032 852;1032 851;1031 850;1030 849;1029 848;1028 847;1027 847;1026 847;1025 846]</pose>
      <pose>[1052 863;1052 864;1051 865;1050 866;1049 867;1048 867;1047 867;1046 866;1045 865;1044 864;1043 863;1042 862;1041 861;1040 860;1039 859;1038 859;1037 858;1036 857;1035 856;1034 855;1034 854;1033 853;1032 852;1032 851;1032 850;1031 849;1030 848;1029 847]</pose>
      <pose>[1057 863;1056 863;1055 863;1054 863;1053 863;1052 863;1051 864;1050 865;1049 865;1048 866;1047 866;1046 866;1045 865;1044 864;1043 863;1042 862;1041 861;1040 860;1039 859;1038 858;1037 858;1036 857;1035 856;1034 855;1033 854;1033 853;1032 852;1032 851;1031 850;1031 849;1031 848]</pose>
      <pose>[1058 868;1058 867;1058 866;1057 865;1056 864;1055 863;1054 863;1053 863;1052 863;1051 864;1050 865;1049 866;1048 866;1047 866;1046 866;1045 865;1044 864;1043 863;1042 862;1041 861;1040 860;1039 859;1038 859;1037 858;1036 857;1035 856]</pose>
      <pose>[1062 874;1061 874;1060 874;1059 873;1058 872;1058 871;1058 870;1058 869;1058 868;1058 867;1058 866;1057 865;1056 864;1055 864;1054 864;1053 864;1052 864;1051 864;1050 864;1049 864;1048 865;1047 865;1046 865;1045 865;1044 865;1043 864;1042 863;1041 862;1040 861;1039 860;1039 859;1039 858]</pose>
      <pose>[1068 876;1067 876;1066 876;1065 876;1064 875;1063 875;1062 875;1061 875;1060 874;1059 873;1058 872;1058 871;1058 870;1058 869;1058 868;1057 867;1056 866;1055 865;1054 864;1053 864;1052 864;1051 864;1050 864;1049 864;1048 865;1047 865;1046 865;1045 865;1044 864;1043 863]</pose>
      <pose>[1071 880;1071 879;1070 878;1069 877;1068 876;1067 876;1066 876;1065 875;1064 875;1063 875;1062 875;1061 874;1060 873;1059 872;1058 871;1057 870;1057 869;1057 868;1057 867;1056 866;1055 865;1054 864;1053 864;1052 864;1051 864;1050 864;1049 864;1048 864;1047 865]</pose>
      <pose>[1077 885;1076 885;1075 885;1074 885;1073 884;1072 883;1072 882;1071 881;1071 880;1070 879;1069 878;1068 877;1067 876;1066 875;1065 875;1064 875;1063 875;1062 874;1061 874;1060 873;1059 872;1058 871;1058 870;1057 869;1057 868;1057 867;1056 866;1055 865;1054 864;1053 864;1052 864;1051 863]</pose>
   </Event>
   <Event Type="Forward">
      <pose>[1071 880;1071 879;1070 878;1069 877;1068 876;1067 876;1066 876;1065 876;1064 875;1063 875;1062 875;1061 874;1060 873;1059 872;1058 871;1058 870;1058 869;1057 868;1057 867;1056 866;1055 865;1054 864;1053 864;1052 864;1051 864;1050 864;1049 864;1048 864;1047 865;1046 865]</pose>
      <pose>[1064 876;1063 875;1062 875;1061 874;1060 873;1059 872;1059 871;1058 870;1058 869;1058 868;1057 867;1056 866;1055 865;1054 864;1053 864;1052 864;1051 864;1050 864;1049 865;1048 865;1047 865;1046 865;1045 864;1044 863;1043 862;1043 861;1043 860;1044 859;1044 858;1044 857]</pose>
      <pose>[1058 870;1058 869;1058 868;1057 867;1056 866;1055 865;1054 865;1053 865;1052 865;1051 865;1050 865;1049 865;1048 865;1047 865;1046 865;1045 865;1044 864;1043 863;1043 862;1043 861;1043 860;1043 859;1044 858;1044 857;1044 856;1044 855;1044 854;1043 853;1042 852;1041 852;1040 852;1039 852]</pose>
      <pose>[1055 863;1054 864;1053 865;1052 865;1051 866;1050 866;1049 866;1048 866;1047 866;1046 865;1045 864;1044 863;1043 862;1043 861;1043 860;1043 859;1044 858;1044 857;1044 856;1044 855;1043 854;1042 853;1041 852;1040 852;1039 852;1038 853;1037 853;1036 854;1035 855]</pose>
      <pose>[1058 861;1057 862;1056 862;1055 863;1054 863;1053 864;1052 864;1051 865;1050 866;1049 866;1048 866;1047 866;1046 865;1045 864;1044 863;1043 862;1043 861;1043 860;1043 859;1044 858;1044 857;1044 856;1044 855;1043 854;1042 853;1041 852;1040 852;1039 852;1038 853]</pose>
   </Event>
   <Event Type="Stopped">
      <pose>[1059 862;1058 862;1057 862;1056 862;1055 862;1054 862;1053 863;1052 864;1051 865;1050 865;1049 866;1048 866;1047 866;1046 865;1045 864;1045 863;1044 862;1044 861;1044 860;1044 859;1044 858;1044 857;1044 856;1044 855;1043 854;1042 853;1041 852;1040 852;1039 852]</pose>
   </Event>
   <Event Type="Backwards">
      <pose>[1061 868;1061 867;1061 866;1060 865;1060 864;1059 863;1058 862;1057 862;1056 862;1055 862;1054 863;1053 863;1052 864;1051 865;1050 865;1049 866;1048 866;1047 866;1046 865;1045 864;1044 863;1044 862;1044 861;1044 860;1044 859;1044 858;1044 857;1044 856;1044 855;1043 854;1043 853]</pose>
      <pose>[1062 869;1062 868;1062 867;1061 866;1061 865;1060 864;1059 863;1058 862;1057 862;1056 862;1055 862;1054 862;1053 863;1052 864;1051 864;1050 865;1049 866;1048 866;1047 866;1046 865;1045 864;1044 863;1044 862;1044 861;1044 860;1044 859;1044 858;1044 857;1044 856;1044 855;1044 854]</pose>
   </Event>
   <Event Type="Stopped">
      <pose>[1063 868;1062 867;1062 866;1061 865;1060 864;1059 863;1058 862;1057 862;1056 862;1055 862;1054 863;1053 863;1052 864;1051 864;1050 865;1049 866;1048 866;1047 866;1046 865;1045 864;1044 863;1043 862;1043 861;1043 860;1043 859;1044 858;1044 857;1044 856;1044 855]</pose>
      <pose>[1063 869;1063 868;1063 867;1062 866;1061 865;1060 864;1059 863;1058 862;1057 862;1056 862;1055 862;1054 862;1053 863;1052 864;1051 864;1050 865;1049 866;1048 866;1047 866;1046 865;1045 864;1045 863;1044 862;1044 861;1044 860;1044 859;1044 858;1044 857;1044 856]</pose>
      <pose>[1063 869;1063 868;1062 867;1062 866;1061 865;1060 864;1059 863;1058 862;1057 862;1056 862;1055 862;1054 863;1053 863;1052 864;1051 865;1050 865;1049 866;1048 866;1047 866;1046 865;1045 864;1045 863;1044 862;1044 861;1044 860;1044 859;1044 858;1044 857;1044 856;1044 855]</pose>
   </Event>
   <Event Type="Forward">
      <pose>[1056 863;1055 863;1054 863;1053 864;1052 865;1051 866;1050 866;1049 866;1048 866;1047 866;1046 865;1045 864;1045 863;1044 862;1044 861;1044 860;1044 859;1044 858;1044 857;1044 856;1044 855;1043 854;1042 853;1041 852;1040 852;1039 851;1038 850;1037 850;1036 850;1035 850]</pose>
      <pose>[1050 862;1050 863;1050 864;1049 865;1048 866;1047 866;1046 865;1045 864;1045 863;1044 862;1044 861;1044 860;1044 859;1044 858;1044 857;1044 856;1043 855;1042 854;1041 853;1040 852;1039 852;1038 851;1037 851;1036 850;1035 849;1035 848;1035 847;1035 846;1035 845;1035 844]</pose>
   </Event>
   <Event Type="Heading">
      <pose>[1048 860;1049 861;1050 862;1050 863;1050 864;1049 865;1048 866;1047 866;1046 865;1045 864;1044 863;1044 862;1044 861;1044 860;1044 859;1044 858;1044 857;1044 856;1043 855;1042 854;1041 853;1040 852;1039 851;1038 851;1037 850;1036 850]</pose>
   </Event>
   <Event Type="Rare">
      <pose>[1044 859;1044 860;1044 861;1044 862;1044 863;1045 864;1046 865;1047 866;1048 866;1049 865;1050 864;1050 863;1050 862;1049 861;1048 860;1047 859;1046 858;1045 857;1045 856;1044 855;1044 854;1044 853;1044 852;1044 851;1044 850;1044 849;1044 848;1044 847]</pose>
   </Event>
   <Event Type="Forward">
      <pose>[1045 865;1046 866;1047 866;1048 866;1049 865;1050 864;1050 863;1050 862;1049 861;1048 860;1047 859;1046 858;1045 857;1045 856;1044 855;1044 854;1044 853;1044 852;1044 851;1045 850;1045 849;1045 848;1046 847;1047 846;1047 845;1047 844;1047 843;1046 842]</pose>
      <pose>[1049 862;1049 861;1048 860;1047 859;1046 858;1045 857;1045 856;1044 855;1044 854;1044 853;1044 852;1045 851;1045 850;1045 849;1046 848;1046 847;1047 846;1047 845;1047 844;1046 843;1045 842;1044 841;1043 840;1042 839;1041 838;1040 837;1040 836]</pose>
      <pose>[1043 856;1044 855;1044 854;1044 853;1045 852;1045 851;1046 850;1046 849;1046 848;1047 847;1047 846;1047 845;1047 844;1047 843;1046 842;1045 841;1044 840;1043 839;1042 838;1041 837;1040 836;1040 835;1040 834;1040 833;1040 832;1041 831;1041 830;1042 829;1042 828;1043 827;1043 826;1044 825]</pose>
      <pose>[1047 847;1047 846;1047 845;1047 844;1046 843;1045 842;1044 841;1043 840;1042 839;1041 838;1041 837;1040 836;1040 835;1040 834;1040 833;1040 832;1041 831;1041 830;1042 829;1043 828;1044 827;1044 826;1044 825;1044 824;1044 823;1043 822;1042 821;1041 820;1040 820]</pose>
      <pose>[1045 842;1044 841;1043 840;1042 839;1041 838;1040 837;1040 836;1040 835;1040 834;1040 833;1040 832;1041 831;1042 830;1043 829;1044 828;1044 827;1044 826;1044 825;1044 824;1044 823;1043 822;1042 821;1041 820;1040 819;1039 818;1039 817;1039 816;1039 815;1040 814;1041 813]</pose>
      <pose>[1040 837;1040 836;1040 835;1040 834;1041 833;1041 832;1041 831;1042 830;1043 829;1043 828;1044 827;1044 826;1044 825;1044 824;1043 823;1043 822;1042 821;1041 820;1040 819;1039 818;1039 817;1039 816;1039 815;1040 814;1041 813;1042 812;1043 811;1044 810;1045 809;1045 808;1045 807]</pose>
   </Event>
   <Model>
      <Resize>3</Resize>
      <Weight>[2;2;2.24000000953674;2.82999992370605;3;3;3;3.16000008583069;3.60999989509583;3.60999989509583;4.23999977111816;5;5;5;5;5;5;5;5;5;5;5;5;5;5;4.11999988555908;4.46999979019165;4.23999977111816;4.23999977111816;4.23999977111816;4.23999977111816;4.23999977111816;4.46999979019165;4.11999988555908;5;5;5;5;5;5;5;5;4.46999979019165;4.23999977111816;4.46999979019165;4.11999988555908;5;5;4.46999979019165;5;5;5.65999984741211;5.65999984741211;5.65999984741211;5;5;5.09999990463257;4.46999979019165;4.23999977111816;5;5.65999984741211;5;4.46999979019165;5;5;5;5;5;5;5;5;4.11999988555908;4.46999979019165;4.23999977111816;5;5.65999984741211;5;5.09999990463257;4.46999979019165;4.23999977111816;5;5;5;5;4.23999977111816;4.23999977111816;4.23999977111816;4.23999977111816;4.46999979019165;4.11999988555908;5;5;4.23999977111816;3.60999989509583;2.82999992370605;3.16000008583069;3;3;2.82999992370605;2.24000000953674;2.24000000953674;1.4099999666214;2]</Weight>
      <Colors>[34;32;29;26;24;22;20;16;14;12;12;12;12;12;11;11;11;10;10;10;10;10;10;10;10;9;8;6;7;8;7;6;5;6;3;2;1;1;1;1;2;4;6;7;10;10;10;8;6;4;6;6;6;7;5;4;4;5;5;4;5;5;6;8;8;8;8;7;6;5;4;4;5;9;9;10;10;11;11;11;9;8;8;8;11;11;10;10;14;17;20;22;23;25;27;27;28;30;31;32;30;30;31]</Colors>
   </Model>
</DT5>